{
  "entityType" : "ROLE",
  "entity" : {
    "customerId" : {
      "entityType" : "CUSTOMER",
      "id" : "4557a330-1aa6-11f0-a348-f5235b8e65fc"
    },
    "externalId" : null,
    "name" : "Entity Group Read-only User",
    "permissions" : [ "READ", "RPC_CALL", "READ_CREDENTIALS", "READ_ATTRIBUTES", "READ_TELEMETRY" ],
    "type" : "GROUP",
    "additionalInfo" : {
      "description" : "Autogenerated group role with read-only permissions."
    },
    "id" : {
      "entityType" : "ROLE",
      "id" : "6ef35e50-9490-11f0-a580-cf0c98df7704"
    },
    "ownerId" : {
      "entityType" : "CUSTOMER",
      "id" : "4557a330-1aa6-11f0-a348-f5235b8e65fc"
    }
  },
  "relations" : [ ],
  "attributes" : {
    "SERVER_SCOPE" : [ ]
  }
}